{"meta":{"app":"https://www.npmjs.com/package/jeff","version":"0.2.2","frameRate":25,"scale":1.2,"filtering":["linear","linear"],"mipmapCompatible":true,"compressedMatrices":true,"prerendered":false,"image":"166.png"},"symbols":{"1":{"id":1,"isGraphic":true,"x":11.65,"y":11.9,"w":21.35,"h":35.9,"sx":1,"sy":404,"sw":36,"sh":61,"className":"CapeBas_7"},"3":{"id":3,"isGraphic":true,"x":16,"y":3.9,"w":21,"h":36.35,"sx":1,"sy":213,"sw":36,"sh":62,"className":"Cape_7"},"5":{"id":5,"isGraphic":true,"x":12.8,"y":9.85,"w":24.95,"h":35.3,"sx":1,"sy":643,"sw":42,"sh":60,"className":"CapeBas_6"},"7":{"id":7,"isGraphic":true,"x":12.2,"y":4.1,"w":24.95,"h":35.1,"sx":1,"sy":705,"sw":42,"sh":59,"className":"Cape_6"},"9":{"id":9,"isGraphic":true,"x":9.7,"y":11.9,"w":21.35,"h":35.9,"sx":1,"sy":341,"sw":36,"sh":61,"className":"CapeBas_5"},"11":{"id":11,"isGraphic":true,"x":5,"y":3.9,"w":21,"h":36.35,"sx":1,"sy":277,"sw":36,"sh":62,"className":"Cape_5"},"13":{"id":13,"isGraphic":true,"x":6.65,"y":8.1,"w":15.1,"h":29.2,"sx":1,"sy":161,"sw":26,"sh":50,"className":"CapeBas_4"},"15":{"id":15,"isGraphic":true,"x":0.9,"y":2.65,"w":12.2,"h":30.65,"sx":1,"sy":55,"sw":21,"sh":52,"className":"Cape_4"},"17":{"id":17,"isGraphic":true,"x":12,"y":4.6,"w":27.1,"h":31.5,"sx":1,"sy":821,"sw":46,"sh":53,"className":"CapeBas_3"},"19":{"id":19,"isGraphic":true,"x":8.45,"y":3.7,"w":22.5,"h":33.6,"sx":1,"sy":467,"sw":38,"sh":57,"className":"Cape_3"},"21":{"id":21,"isGraphic":true,"x":12.2,"y":7.65,"w":28.55,"h":31.85,"sx":1,"sy":876,"sw":48,"sh":54,"className":"CapeBas_2"},"23":{"id":23,"isGraphic":true,"x":10.95,"y":4.95,"w":23,"h":33.05,"sx":1,"sy":585,"sw":39,"sh":56,"className":"Cape_2"},"25":{"id":25,"isGraphic":true,"x":15.1,"y":4.6,"w":27.1,"h":31.5,"sx":1,"sy":766,"sw":46,"sh":53,"className":"CapeBas_1"},"27":{"id":27,"isGraphic":true,"x":14.05,"y":3.7,"w":22.5,"h":33.6,"sx":1,"sy":526,"sw":38,"sh":57,"className":"Cape_1"},"29":{"id":29,"isGraphic":true,"x":8.45,"y":8.15,"w":15.1,"h":29.25,"sx":1,"sy":109,"sw":26,"sh":50,"className":"CapeBas_0"},"31":{"id":31,"isGraphic":true,"x":11.3,"y":2.65,"w":12.2,"h":30.65,"sx":1,"sy":1,"sw":21,"sh":52,"className":"Cape_0"}}}